jit_implementation/__init__.py
jit_implementation/coder.py
jit_implementation/decorator.py
jit_implementation/ide.py
jit_implementation-0.1.5.dist-info/LICENSE
jit_implementation-0.1.5.dist-info/METADATA
jit_implementation-0.1.5.dist-info/WHEEL
jit_implementation-0.1.5.dist-info/RECORD
