Metadata-Version: 2.1
Name: jit-implementation
Version: 0.1.5
Summary: JIT Implementation: Code That Writes Itself
Author: Jiri Klimes
Author-email: jiriklimes920@gmail.com
Requires-Python: >=3.12,<4.0
Classifier: Programming Language :: Python :: 3
Classifier: Programming Language :: Python :: 3.12
Requires-Dist: jinja2 (>=3.1.4,<4.0.0)
Requires-Dist: openai (>=1.51.0,<2.0.0)
Requires-Dist: pydantic (>=2.9.2,<3.0.0)
Requires-Dist: rich (>=13.9.1,<14.0.0)
Requires-Dist: ruff (>=0.6.8,<0.7.0)
